nnumbers/__init__.py
nnumbers/__main__.py
nnumbers/core.py
nnumbers/instance.py
nnumbers/network.py
nnumbers/ssh_keypair.py
nnumbers_development-0.1.3.dist-info/licenses/LICENSE
nnumbers_development-0.1.3.dist-info/METADATA
nnumbers_development-0.1.3.dist-info/WHEEL
nnumbers_development-0.1.3.dist-info/entry_points.txt
nnumbers_development-0.1.3.dist-info/top_level.txt
nnumbers_development-0.1.3.dist-info/RECORD
