Metadata-Version: 2.4
Name: nnumbers-development
Version: 0.1.3
Summary: A  CLI tool for managing OpenStack cloud resources with modern Python features
Author-email: Eric Miguel <eric.mrib@gmail.com>
Maintainer-email: Eric Miguel <eric.mrib@gmail.com>
License: MIT
Project-URL: Homepage, https://github.com/your-org/nnumbers-cli
Project-URL: Documentation, https://github.com/your-org/nnumbers-cli#readme
Project-URL: Repository, https://github.com/your-org/nnumbers-cli.git
Project-URL: Issues, https://github.com/your-org/nnumbers-cli/issues
Project-URL: Changelog, https://github.com/your-org/nnumbers-cli/releases
Keywords: openstack,cloud,cli,infrastructure,devops,automation
Classifier: Development Status :: 4 - Beta
Classifier: Environment :: Console
Classifier: Intended Audience :: Developers
Classifier: Intended Audience :: System Administrators
Classifier: License :: OSI Approved :: MIT License
Classifier: Operating System :: OS Independent
Classifier: Programming Language :: Python :: 3
Classifier: Programming Language :: Python :: 3.11
Classifier: Programming Language :: Python :: 3.12
Classifier: Programming Language :: Python :: 3.13
Classifier: Topic :: System :: Systems Administration
Classifier: Topic :: Software Development :: Libraries :: Python Modules
Classifier: Topic :: Utilities
Classifier: Typing :: Typed
Requires-Python: >=3.11
License-File: LICENSE
Requires-Dist: python-openstackclient>=8.1.0
Requires-Dist: cyclopts>=3.18.0
Requires-Dist: loguru>=0.7.3
Requires-Dist: tabulate>=0.9.0
Requires-Dist: typing-extensions>=4.8.0
Dynamic: license-file
